setup.py
aguan_testpip_installs.egg-info/PKG-INFO
aguan_testpip_installs.egg-info/SOURCES.txt
aguan_testpip_installs.egg-info/dependency_links.txt
aguan_testpip_installs.egg-info/not-zip-safe
aguan_testpip_installs.egg-info/top_level.txt
testpip/__init__.py
testpip/test_install.py